{"cameraMode":{"drawMode":0,"name":"Shaded","section":"Shading Mode"},"sceneLighting":false,"audioPlay":false,"sceneViewState":{"showFog":true,"showMaterialUpdate":true,"showSkybox":true,"showFlares":true,"showImageEffects":true,"showParticleSystems":true,"showVisualEffectGraphs":true,"m_FxEnabled":true},"in2DMode":false,"pivot":{"x":-2.396003484725952,"y":9.458586692810059,"z":87.89505767822266},"rotation":{"x":0.03902590647339821,"y":-0.9022017121315002,"z":0.08398999273777008,"w":0.42199042439460757},"size":7.447480201721191,"orthographic":false}